miningpoolhub_py/__init__.py
miningpoolhub_py/exceptions.py
miningpoolhub_py/miningpoolhubapi.py
miningpoolhub_py/urls.py
miningpoolhub_py-1.0.18.dist-info/LICENSE
miningpoolhub_py-1.0.18.dist-info/WHEEL
miningpoolhub_py-1.0.18.dist-info/METADATA
miningpoolhub_py-1.0.18.dist-info/RECORD
