Metadata-Version: 2.1
Name: miningpoolhub-py
Version: 1.0.18
Summary: An async Python wrapper for the Mining Pool Hub REST API
Home-page: https://github.com/CoryKrol/miningpoolhub_py
License: Apache 2
Author: CoryKrol
Author-email: 16892390+CoryKrol@users.noreply.github.com
Requires-Python: >=3.8,<4.0
Classifier: License :: Other/Proprietary License
Classifier: Programming Language :: Python :: 3
Classifier: Programming Language :: Python :: 3.10
Classifier: Programming Language :: Python :: 3.8
Classifier: Programming Language :: Python :: 3.9
Provides-Extra: docs
Requires-Dist: Sphinx (>=4.2.0,<5.0.0); extra == "docs"
Requires-Dist: aiohttp (>=3.7.4,<4.0.0)
Requires-Dist: python-dotenv (>=0.19.2,<0.20.0)
Requires-Dist: sphinx-rtd-theme (>=1.0.0,<2.0.0); extra == "docs"
Requires-Dist: sphinxcontrib-napoleon (>=0.7,<0.8); extra == "docs"
Requires-Dist: yarl (>=1.6.3,<2.0.0)
Project-URL: Repository, https://github.com/CoryKrol/miningpoolhub_py
